woob/__init__.py
woob_qt-0.0.1.dist-info/METADATA
woob_qt-0.0.1.dist-info/WHEEL
woob_qt-0.0.1.dist-info/top_level.txt
woob_qt-0.0.1.dist-info/RECORD
