Metadata-Version: 2.1
Name: woob-qt
Version: 0.0.1
Summary: Web Outside Of Browsers
Home-page: https://woob.tech
Author: Romain Bignon
Author-email: romain@bignon.me
License: UNKNOWN
Platform: UNKNOWN
Classifier: Programming Language :: Python :: 3
Classifier: Operating System :: OS Independent
Requires-Python: >=3.6
